README.md
setup.cfg
setup.py
topopt/__init__.py
topopt/boundary_conditions.py
topopt/cli.py
topopt/filters.py
topopt/guis.py
topopt/problems.py
topopt/solvers.py
topopt/utils.py
topopt/von_mises_stress.py
topopt.egg-info/PKG-INFO
topopt.egg-info/SOURCES.txt
topopt.egg-info/dependency_links.txt
topopt.egg-info/requires.txt
topopt.egg-info/top_level.txt