Metadata-Version: 2.1
Name: topopt
Version: 0.0.1a1
Summary: A Python Library for Topology Optimization
Home-page: https://github.com/zfergus/topopt
Author: Zachary Ferguson
Author-email: zfergus@nyu.edu
License: MIT
Project-URL: Bug Reports, https://github.com/zfergus/topopt/issues
Project-URL: Source, https://github.com/zfergus/topopt/
Keywords: Topology Optimization,Sturctural Optimization,Simulation
Platform: UNKNOWN
Classifier: Development Status :: 3 - Alpha
Classifier: Intended Audience :: Science/Research
Classifier: Intended Audience :: Developers
Classifier: Topic :: Scientific/Engineering
Classifier: License :: OSI Approved :: MIT License
Classifier: Programming Language :: Python :: 3
Classifier: Programming Language :: Python :: 3.5
Classifier: Programming Language :: Python :: 3.6
Classifier: Programming Language :: Python :: 3.7
Classifier: Programming Language :: Python :: 3.8
Requires-Python: >= 3.5
